mechanical_markdown/__init__.py
mechanical_markdown/__main__.py
mechanical_markdown/command.py
mechanical_markdown/parsers.py
mechanical_markdown/recipe.py
mechanical_markdown/step.py
tests/__init__.py
tests/fake_http_server.py
tests/test_link_validation.py
tests/test_mechanical_markdown.py
mechanical_markdown-0.7.0.dist-info/LICENSE
mechanical_markdown-0.7.0.dist-info/METADATA
mechanical_markdown-0.7.0.dist-info/WHEEL
mechanical_markdown-0.7.0.dist-info/entry_points.txt
mechanical_markdown-0.7.0.dist-info/top_level.txt
mechanical_markdown-0.7.0.dist-info/RECORD
