Metadata-Version: 2.1
Name: mechanical-markdown
Version: 0.7.0
Summary: Run markdown recipes as shell scripts
Home-page: https://github.com/dapr/mechanical-markdown
Author: Charlie Stanley
Author-email: Charlie.Stanley@microsoft.com
License: MIT
Platform: UNKNOWN
Classifier: License :: OSI Approved :: MIT License
Classifier: Programming Language :: Python :: 3
Classifier: Programming Language :: Python :: 3.7
Requires-Dist: termcolor
Requires-Dist: pyyaml
Requires-Dist: mistune (>=3.0.0)
Requires-Dist: requests
Requires-Dist: colorama
